xutilities/__init__.py
xutilities/numeric.py
xutilities/sysutils.py
xutilities-0.1.5.dist-info/LICENSE
xutilities-0.1.5.dist-info/METADATA
xutilities-0.1.5.dist-info/WHEEL
xutilities-0.1.5.dist-info/top_level.txt
xutilities-0.1.5.dist-info/RECORD
