Metadata-Version: 2.1
Name: xutilities
Version: 0.1.5
Summary: System utilities.
Home-page: https://github.com/stbraun/xutilities
Author: Stefan Braun
Author-email: sb@stbraun.com
License: MIT license
Keywords: xutilities
Platform: UNKNOWN
Classifier: Development Status :: 3 - Alpha
Classifier: Intended Audience :: Developers
Classifier: License :: OSI Approved :: MIT License
Classifier: Natural Language :: English
Classifier: Programming Language :: Python :: 3
Classifier: Programming Language :: Python :: 3.7
Classifier: Programming Language :: Python :: 3.8
Classifier: Programming Language :: Python :: 3.9
